{
  "collectionName": "components_shared_features",
  "info": {
    "displayName": "Feature",
    "icon": "bulletList",
    "description": "Icon + title + description card"
  },
  "options": {},
  "attributes": {
    "icon": {
      "type": "string"
    },
    "title": {
      "type": "string"
    },
    "subtitle": {
      "type": "string"
    },
    "description": {
      "type": "text"
    },
    "value": {
      "type": "string"
    },
    "linkLabel": {
      "type": "string"
    },
    "linkHref": {
      "type": "string"
    }
  }
}
